django_smart_manager-1.2.0.dist-info/METADATA
django_smart_manager-1.2.0.dist-info/RECORD
django_smart_manager-1.2.0.dist-info/WHEEL
django_smart_manager-1.2.0.dist-info/top_level.txt
smart_manager/__init__.py
smart_manager/admin.py
smart_manager/apps.py
smart_manager/base.py
smart_manager/models.py
smart_manager/signal_handlers.py
smart_manager/version.py
smart_manager/migrations/0001_initial.py
smart_manager/migrations/__init__.py
smart_manager/tests/__init__.py
smart_manager/tests/admin_tests.py
smart_manager/tests/base_tests.py
smart_manager/tests/models.py
smart_manager/tests/models_tests.py
smart_manager/tests/smart_managers.py
smart_manager/tests/migrations/0001_initial.py
smart_manager/tests/migrations/__init__.py
