Metadata-Version: 2.1
Name: django-smart-manager
Version: 1.2.0
Summary: Make templates that manage models
Home-page: https://github.com/ambitioninc/django-smart-manager
Author: Wes Kendall
Author-email: opensource@ambition.com
License: MIT
Keywords: Django,Models,ORM,Manager,Templates
Platform: UNKNOWN
Classifier: Programming Language :: Python
Classifier: Programming Language :: Python :: 3.6
Classifier: Programming Language :: Python :: 3.7
Classifier: Intended Audience :: Developers
Classifier: License :: OSI Approved :: MIT License
Classifier: Operating System :: OS Independent
Classifier: Framework :: Django
Classifier: Framework :: Django :: 2.0
Classifier: Framework :: Django :: 2.1
Classifier: Framework :: Django :: 2.2
Requires-Dist: Django (>=2.0)
Requires-Dist: django-manager-utils (>=1.4.0)
Requires-Dist: jsonfield (>=0.9.20)
